pyschemaexplorer/__init__.py
pyschemaexplorer/mai.py
pyschemaexplorer-0.0.1.dist-info/METADATA
pyschemaexplorer-0.0.1.dist-info/WHEEL
pyschemaexplorer-0.0.1.dist-info/licenses/LICENSE
pyschemaexplorer-0.0.1.dist-info/RECORD
