Metadata-Version: 2.1
Name: pyschemaexplorer
Version: 0.0.1
Summary: A package to generate documentation from database
Project-URL: Homepage, https://framagit.org/hacking4me/pyschemaexplorer
Project-URL: Issues, https://framagit.org/hacking4me/pyschemaexplorer/issues
Author-email: RENARD Jean-Baptiste <renardjb@gmail.com>
License-File: LICENSE
Classifier: License :: OSI Approved :: GNU General Public License v3 or later (GPLv3+)
Classifier: Operating System :: OS Independent
Classifier: Programming Language :: Python :: 3
Requires-Python: >=3.10
